{
    "title": "Rescatan a 500 migrantes del Mar Mediterr\u00e1neo",
    "description": "(3 Aug 2017) RESTRICTION SUMMARY: \r\nSTORYLINE: \r\nUnos 500 migrantes llegaron al Puerto siciliano de Catania la ma\u00f1ana del jueves, luego de ser rescatados en el mar por un grupo humanitario espa\u00f1ol.\r\nEl grupo Proactiva Open Arms inform\u00f3 que rescat\u00f3 a 494 migrantes, incluyendo a 119 que sobrevivieron un naufragio.\r\nOcho cuerpos fueron recuperados del naufragio. Los sobrevivientes dijeron que adem\u00e1s de esas, otras tres personas se hab\u00edan ahogado, dijo Proactiva Open Arms.\r\nEntre los sobrevivientes se encontraba una ni\u00f1a de dos a\u00f1os que perdi\u00f3 a su madre y a su hermano mayor.\r\nSeg\u00fan la agencia de Naciones Unidas para la inmigraci\u00f3n, entre enero y el 26 de julio de este a\u00f1o, 94.802 migrantes llegaron a Italia, que representa 85% de lo percibido por toda Europa. Se calcula que 2.221 personas han muerto ahogadas intentando de cruzar en lo que va de a\u00f1o. \r\n===SOURCE: AP===\r\n===========================================================\r\nClients are reminded: \r\n(i) to check the terms of their licence agreements for use of content outside news programming and that further advice and assistance can be obtained from the AP Archive on: Tel +44 (0) 20 7482 7482 Email: info@aparchive.com\r\n(ii) they should check with the applicable collecting society in their Territory regarding the clearance of any sound recording or performance included within the AP Television News service \r\n(iii) they have editorial responsibility for the use of all and any content included within the AP Television News service and for libel, privacy, compliance and third party rights applicable to their Territory.\r\n\r\n\r\nYou can license this story through AP Archive: http:\/\/www.aparchive.com\/metadata\/youtube\/e49a30a8605b7f67a9e74b4b5ad1de78 \r\nFind out more about AP Archive: http:\/\/www.aparchive.com\/HowWeWork",
    "referenceId": "TBHfOE3lsL4",
    "date_created": "1502214952",
    "date_modified": "1508437329",
    "tags": "",
    "sourceId": "4",
    "status": "approved",
    "visibility": "1",
    "VV_VI": null,
    "engagement_score": null,
    "conversion_score": null,
    "CVV_VI": null,
    "id": "123195748",
    "loginId": "1759045",
    "entityType": "1",
    "titleTextEncoded": "Rescatan-a-500-migrantes-del-Mar-Mediterr\u00e1neo",
    "category": "",
    "tvp_profiles": [
        "18"
    ],
    "tvp_profiles_manual": "",
    "tvp_profiles_maxscore": 1059.0957,
    "VIDEO_LENGTH": "SHORT",
    "duration": 57,
    "settings": "",
    "asset": {
        "type": "youtube",
        "thumbnailUrl": "https:\/\/i.ytimg.com\/vi\/TBHfOE3lsL4\/sddefault.jpg",
        "uploadDate": 1502214952,
        "videoId": "TBHfOE3lsL4",
        "title": "Rescatan a 500 migrantes del Mar Mediterr\u00e1neo",
        "description": "(3 Aug 2017) RESTRICTION SUMMARY: \r\nSTORYLINE: \r\nUnos 500 migrantes llegaron al Puerto siciliano de Catania la ma\u00f1ana del jueves, luego de ser rescatados en el mar por un grupo humanitario espa\u00f1ol.\r\nEl grupo Proactiva Open Arms inform\u00f3 que rescat\u00f3 a 494 migrantes, incluyendo a 119 que sobrevivieron un naufragio.\r\nOcho cuerpos fueron recuperados del naufragio. Los sobrevivientes dijeron que adem\u00e1s de esas, otras tres personas se hab\u00edan ahogado, dijo Proactiva Open Arms.\r\nEntre los sobrevivientes se encontraba una ni\u00f1a de dos a\u00f1os que perdi\u00f3 a su madre y a su hermano mayor.\r\nSeg\u00fan la agencia de Naciones Unidas para la inmigraci\u00f3n, entre enero y el 26 de julio de este a\u00f1o, 94.802 migrantes llegaron a Italia, que representa 85% de lo percibido por toda Europa. Se calcula que 2.221 personas han muerto ahogadas intentando de cruzar en lo que va de a\u00f1o. \r\n===SOURCE: AP===\r\n===========================================================\r\nClients are reminded: \r\n(i) to check the terms of their licence agreements for use of content outside news programming and that further advice and assistance can be obtained from the AP Archive on: Tel +44 (0) 20 7482 7482 Email: info@aparchive.com\r\n(ii) they should check with the applicable collecting society in their Territory regarding the clearance of any sound recording or performance included within the AP Television News service \r\n(iii) they have editorial responsibility for the use of all and any content included within the AP Television News service and for libel, privacy, compliance and third party rights applicable to their Territory.\r\n\r\n\r\nYou can license this story through AP Archive: http:\/\/www.aparchive.com\/metadata\/youtube\/e49a30a8605b7f67a9e74b4b5ad1de78 \r\nFind out more about AP Archive: http:\/\/www.aparchive.com\/HowWeWork",
        "author": "AP Archive",
        "mediaDuration": 57,
        "prettyDuration": "00:00:57",
        "views": "44"
    },
    "transcripts": "",
    "metrics_statistics": ""
}