{
    "title": "Kazuo Ishiguro wins Nobel Prize for Literature",
    "description": "(5 Oct 2017) The 2017 Nobel Prize for Literature was awarded to British novelist Kazuo Ishiguro.\r\nIn announcing the win, the Permanent Secretary of the Swedish Academy, Sara Danius, said Ishiguro had \"in novels of great emotional force has uncovered the abyss beneath our illusory sense of connection with the world.\"\r\n\r\n\r\nYou can license this story through AP Archive: http:\/\/www.aparchive.com\/metadata\/youtube\/c2de84f49680b047803810432cc25501 \r\nFind out more about AP Archive: http:\/\/www.aparchive.com\/HowWeWork",
    "referenceId": "KbX54PHXK8U",
    "date_created": "1507633635",
    "date_modified": "1508436411",
    "tags": "",
    "sourceId": "4",
    "status": "approved",
    "visibility": "1",
    "VV_VI": null,
    "engagement_score": null,
    "conversion_score": null,
    "CVV_VI": null,
    "id": "123185638",
    "loginId": "1759045",
    "entityType": "1",
    "titleTextEncoded": "Kazuo-Ishiguro-wins-Nobel-Prize-for-Literature",
    "category": "",
    "tvp_profiles": [
        "14"
    ],
    "tvp_profiles_manual": "",
    "tvp_profiles_maxscore": 6556.9766,
    "VIDEO_LENGTH": "SHORT",
    "duration": 30,
    "settings": "",
    "asset": {
        "type": "youtube",
        "thumbnailUrl": "https:\/\/i.ytimg.com\/vi\/KbX54PHXK8U\/sddefault.jpg",
        "uploadDate": 1507633635,
        "videoId": "KbX54PHXK8U",
        "title": "Kazuo Ishiguro wins Nobel Prize for Literature",
        "description": "(5 Oct 2017) The 2017 Nobel Prize for Literature was awarded to British novelist Kazuo Ishiguro.\r\nIn announcing the win, the Permanent Secretary of the Swedish Academy, Sara Danius, said Ishiguro had \"in novels of great emotional force has uncovered the abyss beneath our illusory sense of connection with the world.\"\r\n\r\n\r\nYou can license this story through AP Archive: http:\/\/www.aparchive.com\/metadata\/youtube\/c2de84f49680b047803810432cc25501 \r\nFind out more about AP Archive: http:\/\/www.aparchive.com\/HowWeWork",
        "author": "AP Archive",
        "mediaDuration": 30,
        "prettyDuration": "00:00:30",
        "views": "23"
    },
    "transcripts": "",
    "metrics_statistics": ""
}