{
    "title": "Jessica Biel admits mothering doubts",
    "description": "(1 Aug 2017) Jessica Biel admits mothering doubts\r\n\r\nYou can license this story through AP Archive: http:\/\/www.aparchive.com\/metadata\/youtube\/a1d718ea6b4597a5fc027f49a0b31d5d \r\nFind out more about AP Archive: http:\/\/www.aparchive.com\/HowWeWork",
    "referenceId": "jkm0s6pCJR4",
    "date_created": "1502206518",
    "date_modified": "1508437329",
    "tags": "",
    "sourceId": "4",
    "status": "approved",
    "visibility": "1",
    "VV_VI": null,
    "engagement_score": null,
    "conversion_score": null,
    "CVV_VI": null,
    "id": "123195769",
    "loginId": "1759045",
    "entityType": "1",
    "titleTextEncoded": "Jessica-Biel-admits-mothering-doubts",
    "category": "",
    "tvp_profiles": [
        "32"
    ],
    "tvp_profiles_manual": "",
    "tvp_profiles_maxscore": 195.80972,
    "VIDEO_LENGTH": "SHORT",
    "duration": 60,
    "settings": "",
    "asset": {
        "type": "youtube",
        "thumbnailUrl": "https:\/\/i.ytimg.com\/vi\/jkm0s6pCJR4\/sddefault.jpg",
        "uploadDate": 1502206518,
        "videoId": "jkm0s6pCJR4",
        "title": "Jessica Biel admits mothering doubts",
        "description": "(1 Aug 2017) Jessica Biel admits mothering doubts\r\n\r\nYou can license this story through AP Archive: http:\/\/www.aparchive.com\/metadata\/youtube\/a1d718ea6b4597a5fc027f49a0b31d5d \r\nFind out more about AP Archive: http:\/\/www.aparchive.com\/HowWeWork",
        "author": "AP Archive",
        "mediaDuration": 60,
        "prettyDuration": "00:01:00",
        "views": "60"
    },
    "transcripts": "",
    "metrics_statistics": ""
}