{
    "title": "Universal Newsreel",
    "description": "(4 Jul 1967) STORY\r\n7 200 UN 40-54 b&w sound\r\nUniversal Newsreel 1967\r\n\r\n\r\nYou can license this story through AP Archive: http:\/\/www.aparchive.com\/metadata\/youtube\/a7fe4e083b480c8a72963c8b5d4a07a8 \r\nFind out more about AP Archive: http:\/\/www.aparchive.com\/HowWeWork",
    "referenceId": "xyieU4G1xf8",
    "date_created": "1507373833",
    "date_modified": "1508436471",
    "tags": "",
    "sourceId": "4",
    "status": "approved",
    "visibility": "1",
    "VV_VI": null,
    "engagement_score": null,
    "conversion_score": null,
    "CVV_VI": null,
    "id": "123186441",
    "loginId": "1759045",
    "entityType": "1",
    "titleTextEncoded": "Universal-Newsreel",
    "category": "",
    "tvp_profiles": null,
    "tvp_profiles_manual": "",
    "tvp_profiles_maxscore": 0,
    "VIDEO_LENGTH": "SHORT",
    "duration": 48,
    "settings": "",
    "asset": {
        "type": "youtube",
        "thumbnailUrl": "https:\/\/i.ytimg.com\/vi\/xyieU4G1xf8\/sddefault.jpg",
        "uploadDate": 1507373833,
        "videoId": "xyieU4G1xf8",
        "title": "Universal Newsreel",
        "description": "(4 Jul 1967) STORY\r\n7 200 UN 40-54 b&w sound\r\nUniversal Newsreel 1967\r\n\r\n\r\nYou can license this story through AP Archive: http:\/\/www.aparchive.com\/metadata\/youtube\/a7fe4e083b480c8a72963c8b5d4a07a8 \r\nFind out more about AP Archive: http:\/\/www.aparchive.com\/HowWeWork",
        "author": "AP Archive",
        "mediaDuration": 48,
        "prettyDuration": "00:00:48",
        "views": "18"
    },
    "transcripts": "",
    "metrics_statistics": ""
}